{
  "date": "2026-07-21",
  "prev_date": "2026-07-20",
  "trends": {
    "古风世情": {
      "new_count": 1,
      "dropped_count": 1,
      "new_books": [
        "被威胁后，我成了摄政王的掌中娇"
      ],
      "dropped_books": [
        {
          "title": "薄巧慧重生后她功成身退了",
          "intro": "她是深宫最可悲的棋子，一生痴恋错付，被人构陷，连累庇护自己的薄太后离世，含恨自缢。一朝重生，薄巧慧洗尽怯懦，只心藏三念： 一是报太后接济庇护之恩。 二是报栗妙人百般陷害之仇。 三是彻底挣脱深宫枷锁，摆"
        }
      ],
      "top_risers": [
        {
          "title": "表哥他正得发邪",
          "change": "+3"
        },
        {
          "title": "漠北狂沙，暴君嗜宠和亲妻",
          "change": "+3"
        },
        {
          "title": "未婚夫悔婚？我转身嫁纨绔成团宠",
          "change": "+1"
        }
      ],
      "top_fallers": [
        {
          "title": "他囚我于掌心",
          "change": "-3"
        },
        {
          "title": "我一介咸鱼，竟迎娶尚书嫡女",
          "change": "-2"
        },
        {
          "title": "侍妾生存手册",
          "change": "-2"
        }
      ],
      "reads_growth": [
        {
          "title": "表哥他正得发邪",
          "growth": "+4000"
        },
        {
          "title": "长公主的驸马，请自重",
          "growth": "+3000"
        },
        {
          "title": "重生贞观：再续前尘解旧梦",
          "growth": "+3000"
        }
      ],
      "summary": "新增1本上榜；1本掉出（《薄巧慧重生后她功成身退了》）；《表哥他正得发邪》排名上升+3位；《表哥他正得发邪》阅读量+4000。"
    },
    "科幻末世": {
      "new_count": 1,
      "dropped_count": 1,
      "new_books": [
        "亲姐是末世女主？我才是苟王！"
      ],
      "dropped_books": [
        {
          "title": "末世三年后，男友找到劈腿的我",
          "intro": "【末世1vN】【男全洁】【万人迷】【修罗场】 末世后，乔伊为了过好日子，背叛网恋男友，攀上了队伍的大佬。 三年过去，她和大佬感情深厚。 所以哪怕发现男友一直在找她，也当没看见。 直到大佬被害出事，嫌疑"
        }
      ],
      "top_risers": [
        {
          "title": "别惹小祖宗！末世大佬是宠妹狂魔",
          "change": "+7"
        },
        {
          "title": "末世经营：四位大佬蹲我小店打杂",
          "change": "+3"
        },
        {
          "title": "零下80度，我在地下室热得冒汗",
          "change": "+2"
        }
      ],
      "top_fallers": [
        {
          "title": "末世修仙养女儿，清冷佛子杀疯了",
          "change": "-2"
        },
        {
          "title": "末日倒计时，我盯上了男友宿舍",
          "change": "-2"
        },
        {
          "title": "废土：我能看见万物数据",
          "change": "-2"
        }
      ],
      "reads_growth": [
        {
          "title": "宿舍求生：从刷广告开始变强",
          "growth": "+2.8万"
        },
        {
          "title": "别惹小祖宗！末世大佬是宠妹狂魔",
          "growth": "+7000"
        },
        {
          "title": "末世作精女配勾引疯批哥哥",
          "growth": "+3000"
        }
      ],
      "summary": "新增1本上榜；1本掉出（《末世三年后，男友找到劈腿的我》）；《别惹小祖宗！末世大佬是宠妹狂魔》排名上升+7位；《宿舍求生：从刷广告开始变强》阅读量+2.8万。"
    },
    "游戏体育": {
      "new_count": 3,
      "dropped_count": 3,
      "new_books": [
        "列车求生：我的天赋是三选一",
        "全民求生：开局一间茅草棚",
        "国运求生：我靠御兽杀穿莽荒啦"
      ],
      "dropped_books": [
        {
          "title": "全民安全屋：别人囤粮，我囤怪物",
          "intro": "全球被拖入永夜安全屋游戏。 每个人开局一间破木屋，一扇漏风门，一张硬板床。 白天搜物资，夜晚挡怪物。安全屋血量归零，死；玩家生命值归零，也死。 所有人都在囤水、囤粮、囤武器。 只有桑弥，在第一夜打开门"
        },
        {
          "title": "公路求生：我在灵宠空间种田躺赢",
          "intro": "求生+无CP+基建+美食+萌宠+爽文+天灾+系统 全民公路求生，残疾人恢复，植物人清醒，人手一辆三轮车，偏偏刚骨折的沈青越载具是轮椅，坐上面不能自理。 沈青越：“这是BUG，我要投诉！” 求生游戏不止"
        },
        {
          "title": "夜市求生：开局绑定一辆小吃车",
          "intro": "【无CP+女强+求生游戏+经营升级+诡异美食+爽文】 全民被拉进夜市求生游戏，每个人开局一个摊位。 有人卖袜子，顾客没有脚。 有人卖香水，诡异嫌她味道恶心。 有人卖手机壳，顾客连手都没有。 只有姜禾低"
        }
      ],
      "top_risers": [
        {
          "title": "虚拟游戏：NPC竟是全服第一",
          "change": "+3"
        },
        {
          "title": "国运狼人杀，开局和女巫通视野",
          "change": "+3"
        },
        {
          "title": "神级陪玩：电竞少女制霸全场",
          "change": "+2"
        }
      ],
      "top_fallers": [
        {
          "title": "求生游戏：我在童话森林盖树屋",
          "change": "-2"
        },
        {
          "title": "升维游戏：从零开始建设第一领地",
          "change": "-1"
        }
      ],
      "reads_growth": [
        {
          "title": "海上求生：我提前氪金",
          "growth": "+1000"
        },
        {
          "title": "直播：姐哥们太爱主播了怎么办",
          "growth": "+1000"
        },
        {
          "title": "海岛求生：杀杀杀，榜一她杀疯了",
          "growth": "+1000"
        }
      ],
      "summary": "新增3本上榜；3本掉出（《全民安全屋：别人囤粮，我囤怪物》、《公路求生：我在灵宠空间种田躺赢》、《夜市求生：开局绑定一辆小吃车》）；《虚拟游戏：NPC竟是全服第一》排名上升+3位；《海上求生：我提前氪金》阅读量+1000。"
    },
    "女频衍生": {
      "new_count": 1,
      "dropped_count": 1,
      "new_books": [
        "若曦重生嫁康熙"
      ],
      "dropped_books": [
        {
          "title": "斩神：开局变可莉，七夜自闭",
          "intro": "【女频斩神衍生+提瓦特系统+爆笑反差+物理超度+甜宠无虐】 神明复苏，迷雾降临？外神信徒嚣张跋扈？ 池柚根本没在怕，硬生生把绝望高危的残酷世界，玩成了提瓦特全明星的欢乐割草秀。 高阶水鬼试图偷袭盲人少"
        }
      ],
      "top_risers": [
        {
          "title": "穿成华妃崽，团宠公主拿捏全后宫",
          "change": "+8"
        },
        {
          "title": "南部档案不一样的张家人",
          "change": "+5"
        },
        {
          "title": "斩神拽哥的青梅原来是大佬",
          "change": "+2"
        }
      ],
      "top_fallers": [
        {
          "title": "和封腾分手后，孟宴臣把我宠成宝",
          "change": "-9"
        },
        {
          "title": "HP：碧琪的霍格沃兹欢乐冒险",
          "change": "-5"
        },
        {
          "title": "斩神：如我所书？行吧【",
          "change": "-2"
        }
      ],
      "reads_growth": [
        {
          "title": "南部档案不一样的张家人",
          "growth": "+7000"
        },
        {
          "title": "穿成华妃崽，团宠公主拿捏全后宫",
          "growth": "+1000"
        },
        {
          "title": "hp太好了是dlc我们有救了！",
          "growth": "+1000"
        }
      ],
      "summary": "新增1本上榜；1本掉出（《斩神：开局变可莉，七夜自闭》）；《穿成华妃崽，团宠公主拿捏全后宫》排名上升+8位；《南部档案不一样的张家人》阅读量+7000。"
    },
    "玄幻言情": {
      "new_count": 1,
      "dropped_count": 1,
      "new_books": [
        "我靠抽卡系统装高手"
      ],
      "dropped_books": [
        {
          "title": "死后诈尸诅咒，仙门上下悔悔悔",
          "intro": "关山岄十岁穿越，被师尊捡回仙门。 　　二十岁被小师妹陷害，当着全宗上下所有人的面处以极刑。 　　本想着死了就死了，说不定还能穿越回去，谁知死后系统才来。 　　人都死了，绑定系统还有什么用？ 　　关山岄"
        }
      ],
      "top_risers": [
        {
          "title": "死遁文女主离开，我接盘阴湿男主",
          "change": "+6"
        },
        {
          "title": "您的强制爱请查收",
          "change": "+3"
        },
        {
          "title": "我在秘境废墟捡的垃圾都是宝",
          "change": "+2"
        }
      ],
      "top_fallers": [
        {
          "title": "病弱小师妹出剑后，全宗门疯了",
          "change": "-3"
        },
        {
          "title": "休了四个兽夫后，我契约了六个",
          "change": "-2"
        },
        {
          "title": "穿成耽美文女配男主全贴上来了",
          "change": "-1"
        }
      ],
      "reads_growth": [
        {
          "title": "美人师尊翻车后，惨遭两次囚禁",
          "growth": "+7000"
        },
        {
          "title": "8小时修仙，老娘卷哭全世界",
          "growth": "+5000"
        },
        {
          "title": "死遁文女主离开，我接盘阴湿男主",
          "growth": "+5000"
        }
      ],
      "summary": "新增1本上榜；1本掉出（《死后诈尸诅咒，仙门上下悔悔悔》）；《死遁文女主离开，我接盘阴湿男主》排名上升+6位；《美人师尊翻车后，惨遭两次囚禁》阅读量+7000。"
    },
    "种田": {
      "new_count": 1,
      "dropped_count": 1,
      "new_books": [
        "身怀武力和空间，独自逃荒杀疯了"
      ],
      "dropped_books": [
        {
          "title": "逃荒前，赘爹失败后，我另抱大腿",
          "intro": "【逃荒+种田+情报系统+家长里短+无CP】 安溪穿越了。 没有大杀四方，没有锦衣玉食，只有啃不完的窝窝头跟一个混不吝的爹。 都说穿越到古代活不过十集，她稍微好点，活到了十来岁，然后被人大卸八块，拆吃入"
        }
      ],
      "top_risers": [
        {
          "title": "兽世团宠：幼崽的基建囤货日常",
          "change": "+3"
        },
        {
          "title": "摆摊养崽，我做的美食馋哭古人",
          "change": "+3"
        },
        {
          "title": "破庙通古今，小乞丐们有救啦！",
          "change": "+3"
        }
      ],
      "top_fallers": [
        {
          "title": "穿成抛弃糟糠之妻的穷酸秀才",
          "change": "-3"
        },
        {
          "title": "周家独苗要科举",
          "change": "-2"
        },
        {
          "title": "真千金替嫁流放，空间囤货亿点点",
          "change": "-1"
        }
      ],
      "reads_growth": [
        {
          "title": "家徒四壁我养活两个兽世哥哥",
          "growth": "+1.1万"
        },
        {
          "title": "真千金替嫁流放，空间囤货亿点点",
          "growth": "+3000"
        },
        {
          "title": "生七个娃逃荒？我的马车无限囤货",
          "growth": "+2000"
        }
      ],
      "summary": "新增1本上榜；1本掉出（《逃荒前，赘爹失败后，我另抱大腿》）；《兽世团宠：幼崽的基建囤货日常》排名上升+3位；《家徒四壁我养活两个兽世哥哥》阅读量+1.1万。"
    },
    "年代": {
      "new_count": 2,
      "dropped_count": 2,
      "new_books": [
        "丰腴美人一撒娇，冷面军官脸红了",
        "散打冠军在六零嘎嘎乱杀"
      ],
      "dropped_books": [
        {
          "title": "一个农村姑娘的坎坷人生",
          "intro": "1977年，我来到这个世界，第一口呼吸的不是空气，而是牛槽里冰冷的脏水。只因我是女孩，亲奶奶要将我活活溺死。 我被扔在荒山，被狼叼走，又被好心人捡回，以为终于有了家。可温暖是短暂的，养姥爷惨死，我成了"
        },
        {
          "title": "小嘴叭叭姜糖，哑巴哈哈裴蘅",
          "intro": "【七零年代+金手指】【性格冷静+拒绝恋爱脑】【男主姜糖脑+长嘴】 “妈，我长大了。” “我真的长大了。“ “您，可以离婚，我支持您。” 周秀梅震惊：“小孩子，瞎说什么，哪有亲闺女劝爸妈离婚的？” 姜糖"
        }
      ],
      "top_risers": [
        {
          "title": "八零前妻要再婚，前夫半夜爬墙来",
          "change": "+9"
        },
        {
          "title": "渣哥要我做德华，我拿渣哥当跳板",
          "change": "+5"
        },
        {
          "title": "作精大姐大重生，禁欲大佬失控了",
          "change": "+4"
        }
      ],
      "top_fallers": [
        {
          "title": "穿越六零：烈士孤女不做垫脚石",
          "change": "-5"
        },
        {
          "title": "七零：亲爹把我许给京圈大佬后",
          "change": "-4"
        },
        {
          "title": "认错军官对象，都撩上勾了，咋整",
          "change": "-1"
        }
      ],
      "reads_growth": [
        {
          "title": "糙汉军官在大西北养了个娇气包",
          "growth": "+6000"
        },
        {
          "title": "骗婚捞女？科研大佬独宠丰腴美人",
          "growth": "+6000"
        },
        {
          "title": "穿越七零之路人甲日常",
          "growth": "+6000"
        }
      ],
      "summary": "新增2本上榜；2本掉出（《一个农村姑娘的坎坷人生》、《小嘴叭叭姜糖，哑巴哈哈裴蘅》）；《八零前妻要再婚，前夫半夜爬墙来》排名上升+9位；《糙汉军官在大西北养了个娇气包》阅读量+6000。"
    },
    "现言脑洞": {
      "new_count": 2,
      "dropped_count": 2,
      "new_books": [
        "穿成男频文男主的虚荣妹妹",
        "星际强宠：大佬的五个疯批好难哄"
      ],
      "dropped_books": [
        {
          "title": "捞女主播她自带神豪马甲！",
          "intro": "评分低是因为刚开！后续会涨到9以上！ 【女本位+直播＋神豪马甲+无cp＋变美+万人迷男女通杀＋搞钱】 夏弥是个美貌配不上自身野心的女人，她努力挣钱，想做自己的女娲（后天变美）。 一朝神豪系统降临，她终"
        },
        {
          "title": "变美：好热，你这系统正经吗？",
          "intro": "［直播+1vn+雄竞+万人迷+男洁］ 送外卖的第五天，乔薇被车撞了，但戏剧性的是，在身体腾空而起的那一刻她绑定了［逆袭人生］模拟器。 乔薇知道，她改变命运的机会终于来了。 减肥、变美、直播，就在生活变"
        }
      ],
      "top_risers": [
        {
          "title": "高危漫画路人自救指南",
          "change": "+2"
        },
        {
          "title": "狐狸精下山，顶级万人迷训狗守则",
          "change": "+2"
        },
        {
          "title": "穿成动物后我萌翻全网！",
          "change": "+2"
        }
      ],
      "top_fallers": [
        {
          "title": "她又结婚了？",
          "change": "-3"
        }
      ],
      "reads_growth": [
        {
          "title": "看见弹幕时白月光回国了",
          "growth": "+5.0万"
        },
        {
          "title": "拜托，病娇老公是我自己求来的！",
          "growth": "+1.6万"
        },
        {
          "title": "穿成财阀太子爷的作精前女友",
          "growth": "+9000"
        }
      ],
      "summary": "新增2本上榜；2本掉出（《捞女主播她自带神豪马甲！》、《变美：好热，你这系统正经吗？》）；《高危漫画路人自救指南》排名上升+2位；《看见弹幕时白月光回国了》阅读量+5.0万。"
    },
    "宫斗宅斗": {
      "new_count": 1,
      "dropped_count": 1,
      "new_books": [
        "勾了禁欲太子？刚觉醒，被亲哭！"
      ],
      "dropped_books": [
        {
          "title": "他的小玥亮",
          "intro": "（评分刚开 会涨的 双洁的） 人人都说，将军府送进宫的那个晏家女，是个傻子。 早产，迟钝，说话慢半拍，见人就笑。 选妃那天，所有人都笑她：“将军府没人了，送个傻子来充数？” 晏玥听不懂，跟着一起笑。 "
        }
      ],
      "top_risers": [
        {
          "title": "奶娘进府后，绝嗣世子三年抱四子",
          "change": "+4"
        },
        {
          "title": "干啥啥不行，只能生孩子",
          "change": "+2"
        },
        {
          "title": "穿成了揣崽的恶毒公主，只想苟命",
          "change": "+1"
        }
      ],
      "top_fallers": [
        {
          "title": "阴郁万人嫌假千金重生后",
          "change": "-3"
        },
        {
          "title": "爹都认了才告诉我全家都是反贼？",
          "change": "-2"
        },
        {
          "title": "哀家不想听",
          "change": "-2"
        }
      ],
      "reads_growth": [
        {
          "title": "奶娘进府后，绝嗣世子三年抱四子",
          "growth": "+7000"
        },
        {
          "title": "让我做妾？八千禁卫迎我回宫",
          "growth": "+6000"
        },
        {
          "title": "躺又躺不平，咸鱼恪妃宫廷记事",
          "growth": "+2000"
        }
      ],
      "summary": "新增1本上榜；1本掉出（《他的小玥亮》）；《奶娘进府后，绝嗣世子三年抱四子》排名上升+4位；《奶娘进府后，绝嗣世子三年抱四子》阅读量+7000。"
    },
    "悬疑脑洞": {
      "new_count": 2,
      "dropped_count": 2,
      "new_books": [
        "盗墓沙海：江同学魅力值爆表",
        "绑定技能后万人迷被迫陷入修罗场"
      ],
      "dropped_books": [
        {
          "title": "穿进盗笔当采购，全九门都喊我靠",
          "intro": "（主受＋ALL+搞笑＋打工人＋普通人＋部分剧情＋部分日常+小小金手指） 这是女频同人文，怎么一堆男频的人啊，真求你们了，避避雷吧，男频给我把分拉的太离谱了 林越穿越了 一睁眼就在杭州巷子里，全身三百二"
        },
        {
          "title": "睡醒家丢了，我召唤族长振兴张家",
          "intro": "耶咦，居然出评分了，评分刚刚出，比较低。新人出品，先避个雷，无cp＋不和九门玩＋番外和正文无关无关无关＋现有的是黑瞎子和小哥 张守源一觉睡了七百年，醒来家没了，族人没了，只剩一个瘦巴巴的小可怜张麒麟。"
        }
      ],
      "top_risers": [
        {
          "title": "盗笔：嫩牛五方一直在我坟头蹦迪",
          "change": "+3"
        },
        {
          "title": "盗墓：我那柔弱不能自理的本体",
          "change": "+1"
        },
        {
          "title": "盗墓：让瓶邪黑花攻略我",
          "change": "+1"
        }
      ],
      "top_fallers": [
        {
          "title": "盗墓：穿成黑金古刀，小哥求贴贴",
          "change": "-2"
        },
        {
          "title": "我的人格超会演【卡牌扮演】",
          "change": "-1"
        },
        {
          "title": "从南部档案馆靠签到混成九门团宠",
          "change": "-1"
        }
      ],
      "reads_growth": [
        {
          "title": "无限恐怖？反派玩家已上线！",
          "growth": "+1.5万"
        },
        {
          "title": "盗墓：我那柔弱不能自理的本体",
          "growth": "+6000"
        },
        {
          "title": "盗笔：嫩牛五方一直在我坟头蹦迪",
          "growth": "+6000"
        }
      ],
      "summary": "新增2本上榜；2本掉出（《穿进盗笔当采购，全九门都喊我靠》、《睡醒家丢了，我召唤族长振兴张家》）；《盗笔：嫩牛五方一直在我坟头蹦迪》排名上升+3位；《无限恐怖？反派玩家已上线！》阅读量+1.5万。"
    },
    "古言脑洞": {
      "new_count": 0,
      "dropped_count": 0,
      "new_books": [],
      "dropped_books": [],
      "top_risers": [
        {
          "title": "大秦天幕：六公主不想当女帝",
          "change": "+4"
        },
        {
          "title": "听我心声后，九爷连夜抱四爷大腿",
          "change": "+4"
        },
        {
          "title": "女配？我爹是皇帝，你最好也是哦",
          "change": "+1"
        }
      ],
      "top_fallers": [
        {
          "title": "穿古代开幼儿园满朝权贵求学位",
          "change": "-2"
        },
        {
          "title": "我，女配，天幕曝光我是千古一帝",
          "change": "-1"
        },
        {
          "title": "侯府罪妇开天眼，满京权贵藏不住",
          "change": "-1"
        }
      ],
      "reads_growth": [
        {
          "title": "脑子一热，强吻了我哥的同窗好友",
          "growth": "+4.0万"
        },
        {
          "title": "大秦天幕：六公主不想当女帝",
          "growth": "+1.4万"
        },
        {
          "title": "女配？我爹是皇帝，你最好也是哦",
          "growth": "+1.2万"
        }
      ],
      "summary": "《大秦天幕：六公主不想当女帝》排名上升+4位；《脑子一热，强吻了我哥的同窗好友》阅读量+4.0万。"
    },
    "快穿": {
      "new_count": 3,
      "dropped_count": 3,
      "new_books": [
        "快穿：娇软路人甲被一见钟情",
        "命定男主的作精原配觉醒了",
        "男主们轻点亲，她可是恶毒女配啊"
      ],
      "dropped_books": [
        {
          "title": "快穿：恶毒女配？男主都给她当狗",
          "intro": "［万人迷恶毒女配］［道德感低下］［甜宠］［男C］ 姜皎被系统绑定去各个位面扮演里面的恶毒女配，她对这些男主没有任何的愧疚之心，只要漂亮的完成任务就好。 除了，男主全部都要当她的狗。 姜皎觉得很奇怪，她"
        },
        {
          "title": "快穿后就会变成万人迷吗",
          "intro": "【万人迷+快穿+双男主+单箭头多+正文主角无cp+没有副cp】 温望舒被3794绑定后，开始在三千世界里穿梭，顶替原主的身份并帮助原主完成心愿。 3974看着自己有些呆呆的宿主，总有些担心他完成不了任"
        },
        {
          "title": "快穿：绿茶她勾勾手，男主全失控",
          "intro": "新书评分刚出会涨的！【快穿+男洁+无固定CP+男主只偏爱偏袒女主+绿茶+夺爱+一见钟情+微万人迷】 苏蔓灵魂自带特殊体质，她成为炮灰女配，原本高高在上、禁欲薄情的男主，通通失控上位者低头！ 【世界一："
        }
      ],
      "top_risers": [
        {
          "title": "【快穿】心机诱宠，上位攻略",
          "change": "+4"
        },
        {
          "title": "快穿之成为心机白莲花",
          "change": "+1"
        },
        {
          "title": "开局穿渣男？笑话！软饭我吃定了",
          "change": "+1"
        }
      ],
      "top_fallers": [
        {
          "title": "甩了偏执前任后被迫回来哄夫",
          "change": "-4"
        },
        {
          "title": "快穿：嘿嘿，大馋丫头来了！",
          "change": "-1"
        },
        {
          "title": "快穿：甜文里的对照组",
          "change": "-1"
        }
      ],
      "reads_growth": [
        {
          "title": "【快穿】心机诱宠，上位攻略",
          "growth": "+6000"
        },
        {
          "title": "掠夺成瘾！",
          "growth": "+6000"
        },
        {
          "title": "快穿强制爱：病娇大佬夺她上瘾",
          "growth": "+6000"
        }
      ],
      "summary": "新增3本上榜；3本掉出（《快穿：恶毒女配？男主都给她当狗》、《快穿后就会变成万人迷吗》、《快穿：绿茶她勾勾手，男主全失控》）；《【快穿】心机诱宠，上位攻略》排名上升+4位；《【快穿】心机诱宠，上位攻略》阅读量+6000。"
    },
    "青春甜宠": {
      "new_count": 2,
      "dropped_count": 2,
      "new_books": [
        "【酸or涩】",
        "缪斯要分手"
      ],
      "dropped_books": [
        {
          "title": "我，怂且恶毒",
          "intro": "【女主重生+男主系统】 【怂且恶毒窝窝囊囊干坏事女主x口嫌体正直男妈妈男主】 云落没想过她这种人还能重生。 按理来说，她该下地狱的。 为什么重生了 还回到了高中。 ……高中确实挺像地狱的。 _ 南宴没"
        },
        {
          "title": "海后日常崩大佬，手滑建了个群",
          "intro": "【穿书+万人迷+强取豪夺+强制爱+多男主+男全洁+雄竞修罗场+1VN】 【避雷：律师男主交往过女朋友，牵手拥抱过，非高洁】 母单娇软小社恐苏星若穿成了同名同姓恶毒捞金海后。 开局就是修罗场——鱼塘里的"
        }
      ],
      "top_risers": [
        {
          "title": "弟弟用我照片，网恋疯批太子爷",
          "change": "+2"
        }
      ],
      "top_fallers": [
        {
          "title": "在帅哥评论区口嗨掉马后",
          "change": "-1"
        },
        {
          "title": "泥珠",
          "change": "-1"
        }
      ],
      "reads_growth": [
        {
          "title": "在帅哥评论区口嗨掉马后",
          "growth": "+2.8万"
        },
        {
          "title": "我刻薄不是装的",
          "growth": "+2.4万"
        },
        {
          "title": "盛夏青苹果",
          "growth": "+2.0万"
        }
      ],
      "summary": "新增2本上榜；2本掉出（《我，怂且恶毒》、《海后日常崩大佬，手滑建了个群》）；《弟弟用我照片，网恋疯批太子爷》排名上升+2位；《在帅哥评论区口嗨掉马后》阅读量+2.8万。"
    },
    "星光璀璨": {
      "new_count": 2,
      "dropped_count": 2,
      "new_books": [
        "老公去救她？我重生闪婚当警嫂！",
        "不是，这个主播她纯隔应人"
      ],
      "dropped_books": [
        {
          "title": "黑道大佬重生偶像练习生后爆红了",
          "intro": "【无cp+男主视角+男团选秀+C位出道】 评分刚出，会慢慢涨的。 盛天集团的二把手沈夜白退休第一天，溺水而亡。 再睁眼时，他成了一个被霸凌、不会唱跳、顶着粉毛的男团练习生。 初舞台当天。 导师：“你的"
        },
        {
          "title": "别给黑红女主播送钱，会变成狗",
          "intro": "（刚开分，会涨） 非恶女，女主是成长型女主！！！ 女主其实很萌萌萌，万人迷。前期开黑帖多，后面会爽起来，会离开原公司。 女主会理所应当的捞大哥钱，但不会理所应当捞大姐、粉丝的钱。 【万人迷+直播+多男"
        }
      ],
      "top_risers": [
        {
          "title": "勇闯娱乐圈，从群演干到影后！",
          "change": "+2"
        },
        {
          "title": "团播：穿成恶女！拿下女主神豪团",
          "change": "+2"
        },
        {
          "title": "当高考状元穿成娱乐圈黑红女星",
          "change": "+1"
        }
      ],
      "top_fallers": [
        {
          "title": "哥哥的柠檬糖",
          "change": "-2"
        },
        {
          "title": "素人选秀？顶流导师是我学生",
          "change": "-1"
        },
        {
          "title": "文娱：妹宝太强，哥哥们躺赢了",
          "change": "-1"
        }
      ],
      "reads_growth": [
        {
          "title": "万人迷神颜顶流只想演炮灰",
          "growth": "+2.0万"
        },
        {
          "title": "当高考状元穿成娱乐圈黑红女星",
          "growth": "+1.1万"
        },
        {
          "title": "重生08娱乐圈：女顶流她杀疯了",
          "growth": "+3000"
        }
      ],
      "summary": "新增2本上榜；2本掉出（《黑道大佬重生偶像练习生后爆红了》、《别给黑红女主播送钱，会变成狗》）；《勇闯娱乐圈，从群演干到影后！》排名上升+2位；《万人迷神颜顶流只想演炮灰》阅读量+2.0万。"
    },
    "女频悬疑": {
      "new_count": 1,
      "dropped_count": 1,
      "new_books": [
        "盗墓：哭啥？不白嫖！管售后的"
      ],
      "dropped_books": [
        {
          "title": "小道兼职出马仙，精妖鬼怪忙递烟",
          "intro": "【大女主+无CP+无系统+群像+微恐怖+传统】 如果活人的名字写在出马弟子供奉的堂单上，会有什么后果呢？ 在山海关以东的一个小屯子里，孩子遇上小鬼子的阴兵该如何破局？ 那被思想落后溺死的一个又一个女婴"
        }
      ],
      "top_risers": [
        {
          "title": "盗墓：穿越后我是张家人？",
          "change": "+2"
        },
        {
          "title": "九叔：小崽崽他横行无忌",
          "change": "+1"
        },
        {
          "title": "被阴湿杀人魔盯上后【贵族学院】",
          "change": "+1"
        }
      ],
      "top_fallers": [
        {
          "title": "【神夏】她是一条小金鱼",
          "change": "-3"
        },
        {
          "title": "卧底十年归，女局长她雷厉风行",
          "change": "-1"
        },
        {
          "title": "盗墓之从南部档案开始",
          "change": "-1"
        }
      ],
      "reads_growth": [
        {
          "title": "让你破案，你搁这分享犯罪经验？",
          "growth": "+9000"
        },
        {
          "title": "刑侦：我的眼睛就是尺",
          "growth": "+2000"
        },
        {
          "title": "盗墓：穿越后我是张家人？",
          "growth": "+1000"
        }
      ],
      "summary": "新增1本上榜；1本掉出（《小道兼职出马仙，精妖鬼怪忙递烟》）；《盗墓：穿越后我是张家人？》排名上升+2位；《让你破案，你搁这分享犯罪经验？》阅读量+9000。"
    },
    "职场婚恋": {
      "new_count": 2,
      "dropped_count": 2,
      "new_books": [
        "纹心尖",
        "危险分子勿靠近"
      ],
      "dropped_books": [
        {
          "title": "姐姐乖，别动，等小狗爬过去",
          "intro": "疯批阴湿小狗｜年龄差3｜双洁甜宠｜出租屋 唐禧做了场梦才知道自己是一本小说里的恶毒女配，而在她家借住的许厌是世界的男主。 作为一个合格的恶毒女配，在父母意外双亡获得赔偿金后，唐禧会把许厌带进简陋出租屋"
        },
        {
          "title": "儿媳一米八，打完我儿就别打我了",
          "intro": "【正在改编动漫】窝囊了一辈子的山村少年高远在结婚当天被要加彩礼，不堪其辱，跳河自杀，被一老翁救起。一位高高壮壮一米八女生，相亲屡屡遭嫌弃。二人高低搞笑组合，在村里把这家人受的窝囊气一一找补回来。女生最"
        }
      ],
      "top_risers": [
        {
          "title": "向周舟",
          "change": "+3"
        },
        {
          "title": "考个公，竟被大佬盯上了",
          "change": "+3"
        },
        {
          "title": "清冷万人迷每个世界都被强取豪夺",
          "change": "+1"
        }
      ],
      "top_fallers": [
        {
          "title": "真千金她从军了",
          "change": "-4"
        },
        {
          "title": "清冷美人又被强取豪夺",
          "change": "-1"
        },
        {
          "title": "怀孕三月，死去的丈夫失忆回来了",
          "change": "-1"
        }
      ],
      "reads_growth": [
        {
          "title": "考个公，竟被大佬盯上了",
          "growth": "+5000"
        },
        {
          "title": "社恐乖乖女意外怀了红毛的崽后",
          "growth": "+3000"
        },
        {
          "title": "30岁停潮，被年轻医生偏执深宠",
          "growth": "+2000"
        }
      ],
      "summary": "新增2本上榜；2本掉出（《姐姐乖，别动，等小狗爬过去》、《儿媳一米八，打完我儿就别打我了》）；《向周舟》排名上升+3位；《考个公，竟被大佬盯上了》阅读量+5000。"
    },
    "豪门总裁": {
      "new_count": 1,
      "dropped_count": 1,
      "new_books": [
        "穿成财阀男主的心机女秘书"
      ],
      "dropped_books": [
        {
          "title": "联姻骄纵千金，偏执大佬宠上天",
          "intro": "评分刚出，会涨的～【1v1双洁，先婚后爱，全程高甜，大佬重欲偏执又纯情，生理性喜欢，满心满眼只偏爱小娇娇，他超爱！大黄丫头们，都来看吧～】 年上掌控型daddy & 娇纵豪门千金 　京海人人都知道，霍"
        }
      ],
      "top_risers": [
        {
          "title": "妹宝假装被催眠，阴湿哥哥上瘾了",
          "change": "+2"
        },
        {
          "title": "备孕夜睁眼！男主的恶毒前妻觉醒",
          "change": "+2"
        },
        {
          "title": "京圈太子爷：宝宝勾心又勾身呢",
          "change": "+1"
        }
      ],
      "top_fallers": [
        {
          "title": "闪婚老公，婚前不熟婚后猛亲",
          "change": "-2"
        },
        {
          "title": "孕假被拒？可我揣的是总裁的崽",
          "change": "-2"
        },
        {
          "title": "春夜溺吻",
          "change": "-1"
        }
      ],
      "reads_growth": [
        {
          "title": "妹宝假装被催眠，阴湿哥哥上瘾了",
          "growth": "+12.4万"
        },
        {
          "title": "【普女】他们都对我很好奇",
          "growth": "+7000"
        },
        {
          "title": "春夜溺吻",
          "growth": "+5000"
        }
      ],
      "summary": "新增1本上榜；1本掉出（《联姻骄纵千金，偏执大佬宠上天》）；《妹宝假装被催眠，阴湿哥哥上瘾了》排名上升+2位；《妹宝假装被催眠，阴湿哥哥上瘾了》阅读量+12.4万。"
    },
    "民国言情": {
      "new_count": 2,
      "dropped_count": 2,
      "new_books": [
        "偷军火炸炮楼，四岁萌宝横着走！",
        "纳尼！穿成纯种小鬼子啦！天塌了"
      ],
      "dropped_books": [
        {
          "title": "谍战：我的动物军团杀疯了",
          "intro": "乱世狼烟，日寇横行。 孤女禾苗，觉醒万兽之主系统。 鼠潜地道，鸦探长空； 猫狗盯梢，蜂群破阵； 毒蛇隐杀，步步为营。 以鸟兽为耳目，以虫蛇为刀锋。 隐于市井，搅动谍战迷局； 孤身抗敌，踏平倭寇凶焰。 "
        },
        {
          "title": "资本家小姐找的俊老公！人帅腰好",
          "intro": "【穿书+空间＋家国情＋先婚后爱＋体力超好的军阀头子＆温婉漂亮的资本大小姐】 温青岚是25世纪军事学博士，意外穿越来到一本年代文小说里，成了上海滩有名的资本阶级大小姐。 原书中，她喜欢上一个留洋归来的男"
        }
      ],
      "top_risers": [
        {
          "title": "抗战1939：你管这叫卫生员？",
          "change": "+1"
        },
        {
          "title": "碎女子",
          "change": "+1"
        },
        {
          "title": "搬空地主鬼子，我在民国养崽抗战",
          "change": "+1"
        }
      ],
      "top_fallers": [
        {
          "title": "表妹复明后，被疯批少帅强夺了",
          "change": "-4"
        },
        {
          "title": "穿越民国：翠花勇闯特务圈",
          "change": "-1"
        },
        {
          "title": "苦命村妇",
          "change": "-1"
        }
      ],
      "reads_growth": [
        {
          "title": "穿越民国，我爹是东北王",
          "growth": "+7000"
        },
        {
          "title": "穿越民国：翠花勇闯特务圈",
          "growth": "+6000"
        },
        {
          "title": "穷妻",
          "growth": "+5000"
        }
      ],
      "summary": "新增2本上榜；2本掉出（《谍战：我的动物军团杀疯了》、《资本家小姐找的俊老公！人帅腰好》）；《抗战1939：你管这叫卫生员？》排名上升+1位；《穿越民国，我爹是东北王》阅读量+7000。"
    }
  }
}